LICENSE.txt
README
setup.cfg
setup.py
AliProductExtractor/__init__.py
AliProductExtractor/__main__.py
AliProductExtractor/scrape_ali_express.py
AliProductExtractor.egg-info/PKG-INFO
AliProductExtractor.egg-info/SOURCES.txt
AliProductExtractor.egg-info/dependency_links.txt
AliProductExtractor.egg-info/requires.txt
AliProductExtractor.egg-info/top_level.txt